gtkit/__init__.py
gtkit/gops.py
gtkit/gpdops.py
gtkit/imgops.py
gtkit/imutils.py
gtkit/mesh.py
gtkit/mops.py
gtkit-0.1.1.dist-info/LICENSE
gtkit-0.1.1.dist-info/METADATA
gtkit-0.1.1.dist-info/WHEEL
gtkit-0.1.1.dist-info/top_level.txt
gtkit-0.1.1.dist-info/RECORD
