Metadata-Version: 2.1
Name: gtkit
Version: 0.1.1
Summary: A library designed to streamline GIS (Geographic Information System) related tasks. Whether it is geometry, GeoDataFrames, images, or mathematical operations, GTKit provides a set of commonly used methods and operations to simplify your workflow.
Home-page: https://github.com/fuzailpalnak/gtkit
Author: Fuzail Palnak
Author-email: fuzailpalnak@gmail.com
Keywords: Gis utils,Gis Operations,Raster Operations,Geometry Operations
Classifier: Programming Language :: Python :: 3
Classifier: Topic :: Software Development :: Libraries
Classifier: Topic :: Software Development :: Libraries :: Python Modules
Classifier: Intended Audience :: Developers
Classifier: Operating System :: OS Independent
Requires-Python: >=3.6
License-File: LICENSE
